MusicKuwo/Core.py
MusicKuwo/Objects.py
MusicKuwo/Uitls.py
MusicKuwo/__init__.py
MusicKuwo/Domes/MusicDownload.py
MusicKuwo/Domes/__init__.py
MusicKuwo-1.0.0.dist-info/LICENSE
MusicKuwo-1.0.0.dist-info/METADATA
MusicKuwo-1.0.0.dist-info/WHEEL
MusicKuwo-1.0.0.dist-info/top_level.txt
MusicKuwo-1.0.0.dist-info/RECORD
