Metadata-Version: 2.1
Name: MusicKuwo
Version: 1.0.0
Summary: A kuwo music python API.
Home-page: https://github.com/XiaocaicaiGithub/MusicKuwo
Author: Xiaocaicai
Author-email: xiaocaicai_email@sina.com
License: UNKNOWN
Platform: UNKNOWN
Classifier: Programming Language :: Python :: 3
Classifier: License :: OSI Approved :: MIT License
Classifier: Operating System :: OS Independent
Requires-Python: >=3.8.0
License-File: LICENSE
Requires-Dist: requests
